djadmin2/__init__.py
djadmin2/actions.py
djadmin2/admin2.py
djadmin2/apiviews.py
djadmin2/apps.py
djadmin2/core.py
djadmin2/filters.py
djadmin2/forms.py
djadmin2/models.py
djadmin2/permissions.py
djadmin2/renderers.py
djadmin2/settings.py
djadmin2/site.py
djadmin2/types.py
djadmin2/utils.py
djadmin2/viewmixins.py
djadmin2/views.py
djadmin2/migrations/0001_initial.py
djadmin2/migrations/__init__.py
djadmin2/templatetags/__init__.py
djadmin2/templatetags/admin2_tags.py
djadmin2/tests/__init__.py
djadmin2/tests/models.py
djadmin2/tests/test_actions.py
djadmin2/tests/test_admin2tags.py
djadmin2/tests/test_auth_admin.py
djadmin2/tests/test_core.py
djadmin2/tests/test_renderers.py
djadmin2/tests/test_types.py
djadmin2/tests/test_utils.py
djadmin2/tests/test_views.py
djadmin2/tests/urls.py
djadmin2/tests/migrations/0001_initial.py
djadmin2/tests/migrations/__init__.py
djadmin2/tests/templates/djadmin2theme_bootstrap3/custom_login_template.html
djadmin2/themes/__init__.py
djadmin2/themes/djadmin2theme_bootstrap3/__init__.py
djadmin2/themes/djadmin2theme_bootstrap3/static/djadmin2theme_bootstrap3/css/base.css
djadmin2/themes/djadmin2theme_bootstrap3/static/djadmin2theme_bootstrap3/js/actions.js
djadmin2/themes/djadmin2theme_bootstrap3/static/djadmin2theme_bootstrap3/js/base.js
djadmin2/themes/djadmin2theme_bootstrap3/static/djadmin2theme_bootstrap3/js/sb-admin-2.js
djadmin2/themes/djadmin2theme_bootstrap3/static/djadmin2theme_bootstrap3/libs/html5shiv.js
djadmin2/themes/djadmin2theme_bootstrap3/static/djadmin2theme_bootstrap3/libs/jquery.min.js
djadmin2/themes/djadmin2theme_bootstrap3/static/djadmin2theme_bootstrap3/libs/respond.min.js
djadmin2/themes/djadmin2theme_bootstrap3/static/djadmin2theme_bootstrap3/libs/bootstrap/css/bootstrap-theme.min.css
djadmin2/themes/djadmin2theme_bootstrap3/static/djadmin2theme_bootstrap3/libs/bootstrap/css/bootstrap.min.css
django_admin2-0.7.1.dist-info/top_level.txt
django_admin2-0.7.1.dist-info/METADATA
django_admin2-0.7.1.dist-info/DESCRIPTION.rst
django_admin2-0.7.1.dist-info/metadata.json
django_admin2-0.7.1.dist-info/WHEEL
django_admin2-0.7.1.dist-info/RECORD
