Metadata-Version: 2.0
Name: django-admin2
Version: 0.7.1
Summary: An introspective interface for Django's ORM.
Home-page: http://djangoadmin.org
Author: Daniel Greenfeld & Contributors
Author-email: pydanny@gmail.com
License: MIT
Keywords: django,admin
Platform: UNKNOWN
Classifier: Development Status :: 3 - Alpha
Classifier: Environment :: Web Environment
Classifier: Framework :: Django
Classifier: License :: OSI Approved :: BSD License
Classifier: Operating System :: OS Independent
Classifier: Programming Language :: JavaScript
Classifier: Programming Language :: Python :: 2.7
Classifier: Programming Language :: Python :: 3.3
Classifier: Topic :: Internet :: WWW/HTTP
Classifier: Topic :: Internet :: WWW/HTTP :: Dynamic Content
Classifier: Topic :: Software Development :: Libraries :: Python Modules
Requires-Dist: django (>=1.8.0)
Requires-Dist: django-extra-views (==0.8.0)
Requires-Dist: django-braces (>=1.3.0)
Requires-Dist: djangorestframework (<=3.5.3)
Requires-Dist: django-filter (==1.0.0)
Requires-Dist: pytz (==2016.4)
Requires-Dist: future (>=0.15.2)
Provides-Extra: testing
Requires-Dist: pytest; extra == 'testing'
Requires-Dist: pytest-django; extra == 'testing'
Requires-Dist: pytest-ipdb; extra == 'testing'
